baton/__init__.py
baton/api.py
baton/collections.py
baton/json.py
baton/mappers.py
baton/models.py
baton/types.py
baton/_baton/__init__.py
baton/_baton/_baton_runner.py
baton/_baton/_constants.py
baton/_baton/api.py
baton/_baton/baton_access_control_mappers.py
baton/_baton/baton_custom_object_mappers.py
baton/_baton/baton_entity_mappers.py
baton/_baton/baton_metadata_mappers.py
baton/_baton/json.py
baton/tests/__init__.py
baton/tests/_stubs.py
baton/tests/test_collections.py
baton/tests/test_models.py
baton/tests/_baton/__init__.py
baton/tests/_baton/_helpers.py
baton/tests/_baton/_json_helpers.py
baton/tests/_baton/_settings.py
baton/tests/_baton/_stubs.py
baton/tests/_baton/test__baton_runner.py
baton/tests/_baton/test_api.py
baton/tests/_baton/test_baton_access_control_mappers.py
baton/tests/_baton/test_baton_custom_object_mappers.py
baton/tests/_baton/test_baton_entity_mappers.py
baton/tests/_baton/test_baton_metadata_mappers.py
baton/tests/_baton/test_json.py
baton-1.0.2.dist-info/licenses/LICENSE.txt
baton-1.0.2.dist-info/METADATA
baton-1.0.2.dist-info/WHEEL
baton-1.0.2.dist-info/top_level.txt
baton-1.0.2.dist-info/RECORD
