Metadata-Version: 2.4
Name: baton
Version: 1.0.2
Summary: Python wrapper for baton.
Home-page: https://github.com/wtsi-hgi/python-baton-wrapper
Author: Colin Nolan
Author-email: colin.nolan@sanger.ac.uk
License: LGPL
Classifier: Development Status :: 5 - Production/Stable
Classifier: Operating System :: OS Independent
Classifier: Programming Language :: Python :: 3.5
Classifier: License :: OSI Approved :: GNU Lesser General Public License v3 (LGPLv3)
License-File: LICENSE.txt
Requires-Dist: python-dateutil==2.5.3
Requires-Dist: hgijson==1.3.1
Requires-Dist: hgicommon==1.3.2
Dynamic: author
Dynamic: author-email
Dynamic: classifier
Dynamic: description
Dynamic: description-content-type
Dynamic: home-page
Dynamic: license
Dynamic: license-file
Dynamic: requires-dist
Dynamic: summary
